{
  "annotations": {
    "list": [
      {
        "builtIn": 1,
        "datasource": "-- Grafana --",
        "enable": true,
        "hide": true,
        "iconColor": "rgba(0, 211, 255, 1)",
        "name": "Annotations & Alerts",
        "type": "dashboard"
      }
    ]
  },
  "editable": true,
  "gnetId": null,
  "graphTooltip": 0,
  "id": 1,
  "links": [],
  "panels": [
    {
      "alert": {
        "alertRuleTags": {},
        "conditions": [
          {
            "evaluator": {
              "params": [
                12
              ],
              "type": "gt"
            },
            "operator": {
              "type": "and"
            },
            "query": {
              "params": [
                "A",
                "5m",
                "now"
              ]
            },
            "reducer": {
              "params": [],
              "type": "avg"
            },
            "type": "query"
          }
        ],
        "executionErrorState": "alerting",
        "for": "5m",
        "frequency": "1m",
        "handler": 1,
        "name": "CPU usage alert",
        "noDataState": "no_data",
        "notifications": []
      },
      "aliasColors": {},
      "bars": false,
      "dashLength": 10,
      "dashes": false,
      "datasource": null,
      "fieldConfig": {
        "defaults": {
          "color": {},
          "custom": {},
          "thresholds": {
            "mode": "absolute",
            "steps": []
          },
          "unit": "percent"
        },
        "overrides": []
      },
      "fill": 1,
      "fillGradient": 0,
      "gridPos": {
        "h": 9,
        "w": 11,
        "x": 0,
        "y": 0
      },
      "hiddenSeries": false,
      "id": 8,
      "legend": {
        "avg": false,
        "current": false,
        "max": false,
        "min": false,
        "show": true,
        "total": false,
        "values": false
      },
      "lines": true,
      "linewidth": 1,
      "nullPointMode": "null",
      "options": {
        "alertThreshold": true
      },
      "percentage": false,
      "pluginVersion": "7.4.0",
      "pointradius": 2,
      "points": false,
      "renderer": "flot",
      "seriesOverrides": [],
      "spaceLength": 10,
      "stack": false,
      "steppedLine": false,
      "targets": [
        {
          "expr": "100 -(avg by (instance) (rate(node_cpu_seconds_total{job=\"nodeexporter\",mode=\"idle\"}[1m])) * 100)",
          "interval": "",
          "legendFormat": "",
          "refId": "A"
        }
      ],
      "thresholds": [
        {
          "colorMode": "critical",
          "fill": true,
          "line": true,
          "op": "gt",
          "value": 12,
          "visible": true
        }
      ],
      "timeFrom": null,
      "timeRegions": [],
      "timeShift": null,
      "title": "CPU usage",
      "tooltip": {
        "shared": true,
        "sort": 0,
        "value_type": "individual"
      },
      "type": "graph",
      "xaxis": {
        "buckets": null,
        "mode": "time",
        "name": null,
        "show": true,
        "values": []
      },
      "yaxes": [
        {
          "format": "percent",
          "label": null,
          "logBase": 1,
          "max": null,
          "min": null,
          "show": true
        },
        {
          "format": "short",
          "label": null,
          "logBase": 1,
          "max": null,
          "min": null,
          "show": true
        }
      ],
      "yaxis": {
        "align": false,
        "alignLevel": null
      }
    },
    {
      "alert": {
        "alertRuleTags": {},
        "conditions": [
          {
            "evaluator": {
              "params": [
                4
              ],
              "type": "gt"
            },
            "operator": {
              "type": "and"
            },
            "query": {
              "params": [
                "A",
                "5m",
                "now"
              ]
            },
            "reducer": {
              "params": [],
              "type": "avg"
            },
            "type": "query"
          }
        ],
        "executionErrorState": "alerting",
        "for": "5m",
        "frequency": "1m",
        "handler": 1,
        "name": "CPU Load Average alert",
        "noDataState": "no_data",
        "notifications": []
      },
      "aliasColors": {},
      "bars": false,
      "dashLength": 10,
      "dashes": false,
      "datasource": null,
      "decimals": 2,
      "fieldConfig": {
        "defaults": {
          "custom": {}
        },
        "overrides": []
      },
      "fill": 1,
      "fillGradient": 0,
      "gridPos": {
        "h": 9,
        "w": 11,
        "x": 11,
        "y": 0
      },
      "hiddenSeries": false,
      "id": 6,
      "legend": {
        "alignAsTable": true,
        "avg": true,
        "current": true,
        "max": true,
        "min": true,
        "rightSide": false,
        "show": true,
        "total": false,
        "values": true
      },
      "lines": true,
      "linewidth": 1,
      "nullPointMode": "null",
      "options": {
        "alertThreshold": true
      },
      "percentage": false,
      "pluginVersion": "7.4.0",
      "pointradius": 2,
      "points": false,
      "renderer": "flot",
      "seriesOverrides": [],
      "spaceLength": 10,
      "stack": false,
      "steppedLine": false,
      "targets": [
        {
          "expr": "node_load1{instance=\"nodeexporter:9100\", job=\"nodeexporter\"}",
          "interval": "",
          "legendFormat": "LA 1",
          "refId": "A"
        },
        {
          "expr": "node_load5{instance=\"nodeexporter:9100\", job=\"nodeexporter\"}",
          "hide": false,
          "interval": "",
          "legendFormat": "LA 5",
          "refId": "B"
        },
        {
          "expr": "node_load15{instance=\"nodeexporter:9100\", job=\"nodeexporter\"}",
          "hide": false,
          "interval": "",
          "legendFormat": "LA 15",
          "refId": "C"
        }
      ],
      "thresholds": [
        {
          "colorMode": "critical",
          "fill": true,
          "line": true,
          "op": "gt",
          "value": 4,
          "visible": true
        }
      ],
      "timeFrom": null,
      "timeRegions": [],
      "timeShift": null,
      "title": "CPU Load Average",
      "tooltip": {
        "shared": true,
        "sort": 0,
        "value_type": "individual"
      },
      "type": "graph",
      "xaxis": {
        "buckets": null,
        "mode": "time",
        "name": null,
        "show": true,
        "values": []
      },
      "yaxes": [
        {
          "format": "short",
          "label": null,
          "logBase": 1,
          "max": null,
          "min": null,
          "show": true
        },
        {
          "format": "short",
          "label": null,
          "logBase": 1,
          "max": null,
          "min": null,
          "show": true
        }
      ],
      "yaxis": {
        "align": false,
        "alignLevel": null
      }
    },
    {
      "alert": {
        "alertRuleTags": {},
        "conditions": [
          {
            "evaluator": {
              "params": [
                5000000000
              ],
              "type": "lt"
            },
            "operator": {
              "type": "and"
            },
            "query": {
              "params": [
                "A",
                "5m",
                "now"
              ]
            },
            "reducer": {
              "params": [],
              "type": "avg"
            },
            "type": "query"
          }
        ],
        "executionErrorState": "alerting",
        "for": "5m",
        "frequency": "1m",
        "handler": 1,
        "name": "RAM free alert",
        "noDataState": "no_data",
        "notifications": []
      },
      "aliasColors": {},
      "bars": false,
      "dashLength": 10,
      "dashes": false,
      "datasource": null,
      "fieldConfig": {
        "defaults": {
          "color": {},
          "custom": {},
          "thresholds": {
            "mode": "absolute",
            "steps": []
          },
          "unit": "bytes"
        },
        "overrides": []
      },
      "fill": 1,
      "fillGradient": 0,
      "gridPos": {
        "h": 6,
        "w": 11,
        "x": 0,
        "y": 9
      },
      "hiddenSeries": false,
      "id": 4,
      "legend": {
        "avg": false,
        "current": false,
        "max": false,
        "min": false,
        "show": true,
        "total": false,
        "values": false
      },
      "lines": true,
      "linewidth": 1,
      "nullPointMode": "null",
      "options": {
        "alertThreshold": true
      },
      "percentage": false,
      "pluginVersion": "7.4.0",
      "pointradius": 2,
      "points": false,
      "renderer": "flot",
      "seriesOverrides": [],
      "spaceLength": 10,
      "stack": false,
      "steppedLine": false,
      "targets": [
        {
          "expr": "node_memory_MemFree_bytes{instance=\"nodeexporter:9100\", job=\"nodeexporter\"}",
          "interval": "",
          "legendFormat": "",
          "refId": "A"
        }
      ],
      "thresholds": [
        {
          "colorMode": "critical",
          "fill": true,
          "line": true,
          "op": "lt",
          "value": 5000000000,
          "visible": true
        }
      ],
      "timeFrom": null,
      "timeRegions": [],
      "timeShift": null,
      "title": "RAM free",
      "tooltip": {
        "shared": true,
        "sort": 0,
        "value_type": "individual"
      },
      "type": "graph",
      "xaxis": {
        "buckets": null,
        "mode": "time",
        "name": null,
        "show": true,
        "values": []
      },
      "yaxes": [
        {
          "format": "bytes",
          "label": null,
          "logBase": 1,
          "max": null,
          "min": null,
          "show": true
        },
        {
          "format": "short",
          "label": null,
          "logBase": 1,
          "max": null,
          "min": null,
          "show": true
        }
      ],
      "yaxis": {
        "align": false,
        "alignLevel": null
      }
    },
    {
      "datasource": null,
      "fieldConfig": {
        "defaults": {
          "color": {
            "mode": "thresholds"
          },
          "custom": {},
          "mappings": [],
          "thresholds": {
            "mode": "absolute",
            "steps": [
              {
                "color": "green",
                "value": null
              }
            ]
          },
          "unit": "bytes"
        },
        "overrides": []
      },
      "gridPos": {
        "h": 3,
        "w": 4,
        "x": 11,
        "y": 9
      },
      "id": 2,
      "options": {
        "colorMode": "value",
        "graphMode": "none",
        "justifyMode": "auto",
        "orientation": "auto",
        "reduceOptions": {
          "calcs": [
            "lastNotNull"
          ],
          "fields": "",
          "values": false
        },
        "text": {},
        "textMode": "value"
      },
      "pluginVersion": "7.4.0",
      "targets": [
        {
          "expr": "node_memory_MemTotal_bytes{instance=\"nodeexporter:9100\", job=\"nodeexporter\"}",
          "interval": "",
          "legendFormat": "",
          "refId": "A"
        }
      ],
      "timeFrom": null,
      "timeShift": null,
      "title": "RAM total",
      "type": "stat"
    },
    {
      "aliasColors": {},
      "bars": false,
      "dashLength": 10,
      "dashes": false,
      "datasource": null,
      "fieldConfig": {
        "defaults": {
          "custom": {},
          "unit": "bytes"
        },
        "overrides": []
      },
      "fill": 1,
      "fillGradient": 0,
      "gridPos": {
        "h": 9,
        "w": 22,
        "x": 0,
        "y": 15
      },
      "hiddenSeries": false,
      "id": 10,
      "legend": {
        "alignAsTable": false,
        "avg": false,
        "current": true,
        "hideEmpty": false,
        "hideZero": false,
        "max": false,
        "min": false,
        "show": true,
        "total": false,
        "values": true
      },
      "lines": true,
      "linewidth": 1,
      "nullPointMode": "null",
      "options": {
        "alertThreshold": true
      },
      "percentage": false,
      "pluginVersion": "7.4.0",
      "pointradius": 2,
      "points": false,
      "renderer": "flot",
      "seriesOverrides": [],
      "spaceLength": 10,
      "stack": false,
      "steppedLine": false,
      "targets": [
        {
          "expr": "node_filesystem_avail_bytes{fstype!~\"tmpfs|fuse.lxcfs|squashfs\"}",
          "interval": "",
          "legendFormat": "",
          "refId": "A"
        }
      ],
      "thresholds": [],
      "timeFrom": null,
      "timeRegions": [],
      "timeShift": null,
      "title": "Disk free space",
      "tooltip": {
        "shared": true,
        "sort": 0,
        "value_type": "individual"
      },
      "type": "graph",
      "xaxis": {
        "buckets": null,
        "mode": "time",
        "name": null,
        "show": true,
        "values": []
      },
      "yaxes": [
        {
          "format": "bytes",
          "label": null,
          "logBase": 1,
          "max": null,
          "min": null,
          "show": true
        },
        {
          "format": "short",
          "label": null,
          "logBase": 1,
          "max": null,
          "min": null,
          "show": true
        }
      ],
      "yaxis": {
        "align": false,
        "alignLevel": null
      }
    }
  ],
  "refresh": false,
  "schemaVersion": 27,
  "style": "dark",
  "tags": [],
  "templating": {
    "list": []
  },
  "time": {
    "from": "now-30m",
    "to": "now"
  },
  "timepicker": {},
  "timezone": "",
  "title": "My dashboard",
  "uid": "JDDJ0lx7k",
  "version": 2
}